connector_db_tools/__init__.py
connector_db_tools/functions/__init__.py
connector_db_tools/functions/main.py
examples/__init__.py
connector_db_tools-0.0.1.dist-info/LICENSE
connector_db_tools-0.0.1.dist-info/METADATA
connector_db_tools-0.0.1.dist-info/WHEEL
connector_db_tools-0.0.1.dist-info/top_level.txt
connector_db_tools-0.0.1.dist-info/RECORD
