Metadata-Version: 2.1
Name: connector-db-tools
Version: 0.0.1
Summary: connector database
Home-page: https://github.com/jonaqp/connector_db_tools/
Download-URL: https://github.com/jonaqp/connector_db_tools/archive/master.zip
Author: Jonathan Quiza
Author-email: jony327@gmail.com
License: UNKNOWN
Keywords: modin,db,connector
Platform: UNKNOWN
Classifier: Development Status :: 5 - Production/Stable
Classifier: Intended Audience :: Developers
Classifier: Topic :: Scientific/Engineering :: Artificial Intelligence
Classifier: License :: OSI Approved :: Apache Software License
Classifier: Programming Language :: Python :: 3.8
Classifier: Programming Language :: Python :: 3.7
License-File: LICENSE
Requires-Dist: certifi (==2020.4.5.2)
Requires-Dist: cx-Oracle (==8.0.1)
Requires-Dist: modin[all] (==0.8.0)
Requires-Dist: mysqlclient (==1.4.6)
Requires-Dist: numpy (==1.18.1)
Requires-Dist: pandas (==1.0.5)
Requires-Dist: PyMySQL (==0.9.2)
Requires-Dist: pyodbc (==4.0.30)
Requires-Dist: SQLAlchemy (==1.3.17)
Requires-Dist: teradatasql (==17.0.0.2)
Requires-Dist: psutil (==5.7.2)
